ansciier/Ansciier.py
ansciier/__init__.py
ansciier/__main__.py
ansciier/options.py
ansciier-1.2.1.dist-info/LICENSE
ansciier-1.2.1.dist-info/METADATA
ansciier-1.2.1.dist-info/WHEEL
ansciier-1.2.1.dist-info/entry_points.txt
ansciier-1.2.1.dist-info/top_level.txt
ansciier-1.2.1.dist-info/RECORD
