Metadata-Version: 2.1
Name: ansciier
Version: 1.2.1
Summary: Command line program to mimic any image to your terminal
Home-page: https://github.com/Cudiph/ansciier
Author: Cudiph
Author-email: dwiaceromo@gmail.com
License: MIT
Project-URL: Bug Tracker, https://github.com/Cudiph/ansciier/issues
Platform: UNKNOWN
Classifier: Programming Language :: Python :: 3
Classifier: License :: OSI Approved :: MIT License
Classifier: Environment :: Console
Classifier: Topic :: Multimedia
Classifier: Topic :: Multimedia :: Graphics
Classifier: Topic :: Multimedia :: Graphics :: Graphics Conversion
Classifier: Topic :: Multimedia :: Graphics :: Presentation
Classifier: Topic :: Terminals
Requires-Python: >=3.6
Requires-Dist: numpy (>=1.21.0)
Requires-Dist: opencv-python (>=4.5.3.0)
